MANIFEST.in
setup.py
cryptobazen.egg-info/PKG-INFO
cryptobazen.egg-info/SOURCES.txt
cryptobazen.egg-info/dependency_links.txt
cryptobazen.egg-info/not-zip-safe
cryptobazen.egg-info/requires.txt
cryptobazen.egg-info/top_level.txt
cryptobazen/deribit/__init__.py
cryptobazen/deribit/_account_management.py
cryptobazen/deribit/_authentication.py
cryptobazen/deribit/_market_data.py
cryptobazen/deribit/_trading.py
cryptobazen/deribit/_wallet.py