Metadata-Version: 1.0
Name: cryptobazen
Version: 0.3.0
Summary: Wrappers for several exchanges, mainly used for jupyter
Home-page: https://bitbucket.org/salurebi/salure_helpers/
Author: Cryptobazen
Author-email: info@cryptobazen.com
License: N.A.
Platform: UNKNOWN
